securitydev/__init__.py
securitydev/async_client.py
securitydev/client.py
securitydev/exceptions.py
securitydev/py.typed
securitydev/models/__init__.py
securitydev/models/ip_intel.py
securitydev/models/user_intel.py
securitydev/namespaces/__init__.py
securitydev/namespaces/base.py
securitydev/namespaces/ip_intel.py
securitydev/namespaces/user_intel.py
securitydev-1.0.6.dist-info/METADATA
securitydev-1.0.6.dist-info/WHEEL
securitydev-1.0.6.dist-info/licenses/LICENSE
securitydev-1.0.6.dist-info/RECORD
