Metadata-Version: 2.4
Name: securitydev
Version: 1.0.6
Summary: security.dev Python SDK
Project-URL: Homepage, https://security.dev/
Project-URL: Documentation, https://docs.security.dev/
Project-URL: Repository, https://github.com/security-dev/securitydev-python
Author-email: "Felipe R. de Almeida" <hello@security.dev>
License: MIT
License-File: LICENSE
Keywords: security,web
Classifier: Intended Audience :: Developers
Classifier: License :: OSI Approved :: MIT License
Classifier: Operating System :: OS Independent
Classifier: Programming Language :: Python :: 3.8
Classifier: Programming Language :: Python :: 3.9
Classifier: Programming Language :: Python :: 3.10
Classifier: Programming Language :: Python :: 3.11
Classifier: Programming Language :: Python :: 3.12
Classifier: Programming Language :: Python :: 3.13
Classifier: Topic :: Internet
Classifier: Topic :: Security
Classifier: Topic :: Software Development :: Libraries :: Python Modules
Classifier: Typing :: Typed
Requires-Python: >=3.9
Requires-Dist: httpx>=0.28.1
Requires-Dist: pydantic>=2.8.2
